setup.cfg
setup.py
psqldumper/__init__.py
psqldumper/main.py
psqldumper/manager.py
psqldumper.egg-info/PKG-INFO
psqldumper.egg-info/SOURCES.txt
psqldumper.egg-info/dependency_links.txt
psqldumper.egg-info/entry_points.txt
psqldumper.egg-info/namespace_packages.txt
psqldumper.egg-info/top_level.txt
psqldumper/etc/psqldumper.conf.sample