Metadata-Version: 1.0
Name: psqldumper
Version: 0.1.5
Summary: Postgresql dump management helper.
Home-page: https://git.owk.cc/nbrisac/psqldumper
Author: Nicolas Brisac
Author-email: nbrisac@oasiswork.fr
License: MIT
Platform: UNKNOWN
